LICENSE
README.md
setup.cfg
setup.py
connlayer/__init__.py
connlayer/connection_interface.py
connlayer/constants.py
connlayer.egg-info/PKG-INFO
connlayer.egg-info/SOURCES.txt
connlayer.egg-info/dependency_links.txt
connlayer.egg-info/top_level.txt